.bzrignore
LICENSE
README
setup.py
GstEditor.egg-info/PKG-INFO
GstEditor.egg-info/SOURCES.txt
GstEditor.egg-info/dependency_links.txt
GstEditor.egg-info/entry_points.txt
GstEditor.egg-info/requires.txt
GstEditor.egg-info/top_level.txt
gsteditor/__init__.py
gsteditor/bin.py
gsteditor/editor.py
gsteditor/element.py
gsteditor/gsteditor.glade
gsteditor/gsteditor.gladep
gsteditor/pad.py
gsteditor/paramwin.py
gsteditor/version.py