Metadata-Version: 1.0
Name: GstEditor
Version: 0.1.0
Summary: GStreamer Graphical Pipeline Editor
Home-page: http://launchpad.net/gst-editor
Author: Nickolay Bryskin
Author-email: devel.niks@gmail.com
License: GPLv3
Platform: linux
Classifier: Development Status :: 3 - Alpha
Classifier: Environment :: X11 Applications :: Gnome
Classifier: Intended Audience :: Developers
Classifier: Intended Audience :: End Users/Desktop
Classifier: License :: OSI Approved :: GNU General Public License (GPL)
Classifier: Natural Language :: English
Classifier: Operating System :: POSIX :: Linux
Classifier: Programming Language :: Python :: 2.5
Classifier: Topic :: Desktop Environment :: Gnome
Classifier: Topic :: Multimedia :: Sound/Audio :: Capture/Recording
Classifier: Topic :: Multimedia :: Sound/Audio :: Conversion
Classifier: Topic :: Multimedia :: Sound/Audio :: Players
Classifier: Topic :: Multimedia :: Video :: Capture
Classifier: Topic :: Multimedia :: Video :: Conversion
Classifier: Topic :: Multimedia :: Video :: Display
